lc_calc-0.1.dist-info/DESCRIPTION.rst
lc_calc-0.1.dist-info/METADATA
lc_calc-0.1.dist-info/RECORD
lc_calc-0.1.dist-info/WHEEL
lc_calc-0.1.dist-info/entry_points.txt
lc_calc-0.1.dist-info/metadata.json
lc_calc-0.1.dist-info/top_level.txt
lc_calc-0.1.dist-info/zip-safe
src/__init__.py
src/test.py
