Metadata-Version: 2.0
Name: lc-calc
Version: 0.1
Summary: UNKNOWN
Home-page: UNKNOWN
Author: UNKNOWN
Author-email: UNKNOWN
License: UNKNOWN
Platform: UNKNOWN
Requires-Dist: docutils (>=0.3)
Requires-Dist: requests
